{
    "sourceFile": "frontend/src/components/admin/AdminSidebar.tsx",
    "activeCommit": 0,
    "commits": [
        {
            "activePatchIndex": 13,
            "patches": [
                {
                    "date": 1772794830236,
                    "content": "Index: \n===================================================================\n--- \n+++ \n"
                },
                {
                    "date": 1772813321627,
                    "content": "Index: \n===================================================================\n--- \n+++ \n@@ -1,1 +1,86 @@\n-AdminNav\n\\ No newline at end of file\n+\"use client\";\r\n+\r\n+import Link from \"next/link\";\r\n+import { usePathname } from \"next/navigation\";\r\n+import {LayoutDashboard,Users,Tractor,ShoppingCart,Layers,CreditCard,Star,BarChart,Settings,HelpCircle,} from \"lucide-react\";\r\n+\r\n+export default function AdminSidebar() {\r\n+  const pathname = usePathname();\r\n+\r\n+  const linkClass = (path: string) =>\r\n+    `flex items-center gap-3 px-4 py-2 rounded-md text-sm ${\r\n+      pathname === path\r\n+        ? \"bg-green-600 text-white\"\r\n+        : \"text-gray-300 hover:bg-gray-700\"\r\n+    }`;\r\n+\r\n+  return (\r\n+    <aside className=\"w-64 bg-gray-900 text-white min-h-screen p-4\">\r\n+\r\n+      <div className=\"mb-8\">\r\n+        <h2 className=\"text-xl font-bold text-green-500\">\r\n+          AgroShare Admin\r\n+        </h2>\r\n+      </div>\r\n+\r\n+      <nav className=\"space-y-2\">\r\n+\r\n+        <Link href=\"/admin/dashboard\" className={linkClass(\"/admin/dashboard\")}>\r\n+          <LayoutDashboard size={18} />\r\n+          Dashboard\r\n+        </Link>\r\n+\r\n+        <Link href=\"/admin/users\" className={linkClass(\"/admin/users\")}>\r\n+          <Users size={18} />\r\n+          Users\r\n+        </Link>\r\n+\r\n+        <Link href=\"/admin/sellers\" className={linkClass(\"/admin/sellers\")}>\r\n+          <Users size={18} />\r\n+          Sellers\r\n+        </Link>\r\n+\r\n+        <Link href=\"/admin/machines\" className={linkClass(\"/admin/machines\")}>\r\n+          <Tractor size={18} />\r\n+          Machines\r\n+        </Link>\r\n+\r\n+        <Link href=\"/admin/orders\" className={linkClass(\"/admin/orders\")}>\r\n+          <ShoppingCart size={18} />\r\n+          Orders\r\n+        </Link>\r\n+\r\n+        <Link href=\"/admin/categories\" className={linkClass(\"/admin/categories\")}>\r\n+          <Layers size={18} />\r\n+          Categories\r\n+        </Link>\r\n+\r\n+        <Link href=\"/admin/payments\" className={linkClass(\"/admin/payments\")}>\r\n+          <CreditCard size={18} />\r\n+          Payments\r\n+        </Link>\r\n+\r\n+        <Link href=\"/admin/reviews\" className={linkClass(\"/admin/reviews\")}>\r\n+          <Star size={18} />\r\n+          Reviews\r\n+        </Link>\r\n+\r\n+        <Link href=\"/admin/reports\" className={linkClass(\"/admin/reports\")}>\r\n+          <BarChart size={18} />\r\n+          Reports\r\n+        </Link>\r\n+\r\n+        <Link href=\"/admin/settings\" className={linkClass(\"/admin/settings\")}>\r\n+          <Settings size={18} />\r\n+          Settings\r\n+        </Link>\r\n+\r\n+        <Link href=\"/admin/support\" className={linkClass(\"/admin/support\")}>\r\n+          <HelpCircle size={18} />\r\n+          Support\r\n+        </Link>\r\n+\r\n+      </nav>\r\n+    </aside>\r\n+  );\r\n+}\n\\ No newline at end of file\n"
                },
                {
                    "date": 1772882182197,
                    "content": "Index: \n===================================================================\n--- \n+++ \n@@ -1,27 +1,37 @@\n \"use client\";\r\n \r\n import Link from \"next/link\";\r\n import { usePathname } from \"next/navigation\";\r\n-import {LayoutDashboard,Users,Tractor,ShoppingCart,Layers,CreditCard,Star,BarChart,Settings,HelpCircle,} from \"lucide-react\";\r\n+import { LayoutDashboard, Users, Tractor, ShoppingCart, Layers, CreditCard, Star, BarChart, Settings, HelpCircle, } from \"lucide-react\";\r\n+import Image from \"next/image\";\r\n \r\n export default function AdminSidebar() {\r\n   const pathname = usePathname();\r\n \r\n   const linkClass = (path: string) =>\r\n-    `flex items-center gap-3 px-4 py-2 rounded-md text-sm ${\r\n-      pathname === path\r\n-        ? \"bg-green-600 text-white\"\r\n-        : \"text-gray-300 hover:bg-gray-700\"\r\n+    `flex items-center gap-3 px-4 py-3 rounded-xl text-sm font-semibold transition-all duration-200 ${pathname === path\r\n+      ? \"bg-lime-500 text-slate-950 shadow-xl shadow-lime-500/20 scale-[1.02]\"\r\n+      : \"text-slate-400 hover:text-white hover:bg-slate-900\"\r\n     }`;\r\n \r\n   return (\r\n-    <aside className=\"w-64 bg-gray-900 text-white min-h-screen p-4\">\r\n+    <aside className=\"w-72 bg-slate-950 text-slate-100 h-screen sticky top-0 p-8 flex flex-col border-r border-slate-900 overflow-y-auto no-scrollbar\">\r\n \r\n-      <div className=\"mb-8\">\r\n-        <h2 className=\"text-xl font-bold text-green-500\">\r\n-          AgroShare Admin\r\n-        </h2>\r\n+      <div className=\"mb-14 px-2\">\r\n+        <div className=\"flex items-center gap-4 group cursor-pointer\">\r\n+          <div className=\"relative w-12 h-12 p-2 rounded-2xl shadow-xl shadow-lime-500/10 group-hover:scale-110 transition-transform duration-300\">\r\n+            <Image\r\n+              src=\"/images/logo.png\"\r\n+              alt=\"Logo\"\r\n+              fill\r\n+              className=\"object-contain p-1\"\r\n+            />\r\n+          </div>\r\n+          <h2 className=\"text-2xl font-black tracking-tighter text-white\">\r\n+            Agro<span className=\"text-lime-500\">Share</span>\r\n+          </h2>\r\n+        </div>\r\n       </div>\r\n \r\n       <nav className=\"space-y-2\">\r\n \r\n"
                },
                {
                    "date": 1772882191540,
                    "content": "Index: \n===================================================================\n--- \n+++ \n@@ -0,0 +1,96 @@\n+\"use client\";\r\n+\r\n+import Link from \"next/link\";\r\n+import { usePathname } from \"next/navigation\";\r\n+import { LayoutDashboard, Users, Tractor, ShoppingCart, Layers, CreditCard, Star, BarChart, Settings, HelpCircle, } from \"lucide-react\";\r\n+import Image from \"next/image\";\r\n+\r\n+export default function AdminSidebar() {\r\n+  const pathname = usePathname();\r\n+\r\n+  const linkClass = (path: string) =>\r\n+    `flex items-center gap-3 px-4 py-3 rounded-xl text-sm font-semibold transition-all duration-200 ${pathname === path\r\n+      ? \"bg-lime-500 text-slate-950 shadow-xl shadow-lime-500/20 scale-[1.02]\"\r\n+      : \"text-slate-400 hover:text-white hover:bg-slate-900\"\r\n+    }`;\r\n+\r\n+  return (\r\n+    <aside className=\"w-72 bg-slate-950 text-slate-100 h-screen sticky top-0 p-8 flex flex-col border-r border-slate-900 overflow-y-auto no-scrollbar\">\r\n+\r\n+      <div className=\"mb-14 px-2\">\r\n+        <div className=\"flex items-center gap-4 group cursor-pointer\">\r\n+          <div className=\"relative w-12 h-12 bg-white p-2 rounded-2xl shadow-xl shadow-lime-500/10 group-hover:scale-110 transition-transform duration-300\">\r\n+            <Image\r\n+              src=\"/images/logo.png\"\r\n+              alt=\"Logo\"\r\n+              fill\r\n+              className=\"object-contain p-1\"\r\n+            />\r\n+          </div>\r\n+          <h2 className=\"text-2xl font-black tracking-tighter text-white\">\r\n+            Agro<span className=\"text-lime-500\">Share</span>\r\n+          </h2>\r\n+        </div>\r\n+      </div>\r\n+\r\n+      <nav className=\"space-y-2\">\r\n+\r\n+        <Link href=\"/admin/dashboard\" className={linkClass(\"/admin/dashboard\")}>\r\n+          <LayoutDashboard size={18} />\r\n+          Dashboard\r\n+        </Link>\r\n+\r\n+        <Link href=\"/admin/users\" className={linkClass(\"/admin/users\")}>\r\n+          <Users size={18} />\r\n+          Users\r\n+        </Link>\r\n+\r\n+        <Link href=\"/admin/sellers\" className={linkClass(\"/admin/sellers\")}>\r\n+          <Users size={18} />\r\n+          Sellers\r\n+        </Link>\r\n+\r\n+        <Link href=\"/admin/machines\" className={linkClass(\"/admin/machines\")}>\r\n+          <Tractor size={18} />\r\n+          Machines\r\n+        </Link>\r\n+\r\n+        <Link href=\"/admin/orders\" className={linkClass(\"/admin/orders\")}>\r\n+          <ShoppingCart size={18} />\r\n+          Orders\r\n+        </Link>\r\n+\r\n+        <Link href=\"/admin/categories\" className={linkClass(\"/admin/categories\")}>\r\n+          <Layers size={18} />\r\n+          Categories\r\n+        </Link>\r\n+\r\n+        <Link href=\"/admin/payments\" className={linkClass(\"/admin/payments\")}>\r\n+          <CreditCard size={18} />\r\n+          Payments\r\n+        </Link>\r\n+\r\n+        <Link href=\"/admin/reviews\" className={linkClass(\"/admin/reviews\")}>\r\n+          <Star size={18} />\r\n+          Reviews\r\n+        </Link>\r\n+\r\n+        <Link href=\"/admin/reports\" className={linkClass(\"/admin/reports\")}>\r\n+          <BarChart size={18} />\r\n+          Reports\r\n+        </Link>\r\n+\r\n+        <Link href=\"/admin/settings\" className={linkClass(\"/admin/settings\")}>\r\n+          <Settings size={18} />\r\n+          Settings\r\n+        </Link>\r\n+\r\n+        <Link href=\"/admin/support\" className={linkClass(\"/admin/support\")}>\r\n+          <HelpCircle size={18} />\r\n+          Support\r\n+        </Link>\r\n+\r\n+      </nav>\r\n+    </aside>\r\n+  );\r\n+}\n\\ No newline at end of file\n"
                },
                {
                    "date": 1772882232855,
                    "content": "Index: \n===================================================================\n--- \n+++ \n@@ -49,13 +49,8 @@\n           <Users size={18} />\r\n           Sellers\r\n         </Link>\r\n \r\n-        <Link href=\"/admin/machines\" className={linkClass(\"/admin/machines\")}>\r\n-          <Tractor size={18} />\r\n-          Machines\r\n-        </Link>\r\n-\r\n         <Link href=\"/admin/orders\" className={linkClass(\"/admin/orders\")}>\r\n           <ShoppingCart size={18} />\r\n           Orders\r\n         </Link>\r\n@@ -92,101 +87,5 @@\n \r\n       </nav>\r\n     </aside>\r\n   );\r\n-}\n-\"use client\";\r\n-\r\n-import Link from \"next/link\";\r\n-import { usePathname } from \"next/navigation\";\r\n-import { LayoutDashboard, Users, Tractor, ShoppingCart, Layers, CreditCard, Star, BarChart, Settings, HelpCircle, } from \"lucide-react\";\r\n-import Image from \"next/image\";\r\n-\r\n-export default function AdminSidebar() {\r\n-  const pathname = usePathname();\r\n-\r\n-  const linkClass = (path: string) =>\r\n-    `flex items-center gap-3 px-4 py-3 rounded-xl text-sm font-semibold transition-all duration-200 ${pathname === path\r\n-      ? \"bg-lime-500 text-slate-950 shadow-xl shadow-lime-500/20 scale-[1.02]\"\r\n-      : \"text-slate-400 hover:text-white hover:bg-slate-900\"\r\n-    }`;\r\n-\r\n-  return (\r\n-    <aside className=\"w-72 bg-slate-950 text-slate-100 h-screen sticky top-0 p-8 flex flex-col border-r border-slate-900 overflow-y-auto no-scrollbar\">\r\n-\r\n-      <div className=\"mb-14 px-2\">\r\n-        <div className=\"flex items-center gap-4 group cursor-pointer\">\r\n-          <div className=\"relative w-12 h-12 p-2 rounded-2xl shadow-xl shadow-lime-500/10 group-hover:scale-110 transition-transform duration-300\">\r\n-            <Image\r\n-              src=\"/images/logo.png\"\r\n-              alt=\"Logo\"\r\n-              fill\r\n-              className=\"object-contain p-1\"\r\n-            />\r\n-          </div>\r\n-          <h2 className=\"text-2xl font-black tracking-tighter text-white\">\r\n-            Agro<span className=\"text-lime-500\">Share</span>\r\n-          </h2>\r\n-        </div>\r\n-      </div>\r\n-\r\n-      <nav className=\"space-y-2\">\r\n-\r\n-        <Link href=\"/admin/dashboard\" className={linkClass(\"/admin/dashboard\")}>\r\n-          <LayoutDashboard size={18} />\r\n-          Dashboard\r\n-        </Link>\r\n-\r\n-        <Link href=\"/admin/users\" className={linkClass(\"/admin/users\")}>\r\n-          <Users size={18} />\r\n-          Users\r\n-        </Link>\r\n-\r\n-        <Link href=\"/admin/sellers\" className={linkClass(\"/admin/sellers\")}>\r\n-          <Users size={18} />\r\n-          Sellers\r\n-        </Link>\r\n-\r\n-        <Link href=\"/admin/machines\" className={linkClass(\"/admin/machines\")}>\r\n-          <Tractor size={18} />\r\n-          Machines\r\n-        </Link>\r\n-\r\n-        <Link href=\"/admin/orders\" className={linkClass(\"/admin/orders\")}>\r\n-          <ShoppingCart size={18} />\r\n-          Orders\r\n-        </Link>\r\n-\r\n-        <Link href=\"/admin/categories\" className={linkClass(\"/admin/categories\")}>\r\n-          <Layers size={18} />\r\n-          Categories\r\n-        </Link>\r\n-\r\n-        <Link href=\"/admin/payments\" className={linkClass(\"/admin/payments\")}>\r\n-          <CreditCard size={18} />\r\n-          Payments\r\n-        </Link>\r\n-\r\n-        <Link href=\"/admin/reviews\" className={linkClass(\"/admin/reviews\")}>\r\n-          <Star size={18} />\r\n-          Reviews\r\n-        </Link>\r\n-\r\n-        <Link href=\"/admin/reports\" className={linkClass(\"/admin/reports\")}>\r\n-          <BarChart size={18} />\r\n-          Reports\r\n-        </Link>\r\n-\r\n-        <Link href=\"/admin/settings\" className={linkClass(\"/admin/settings\")}>\r\n-          <Settings size={18} />\r\n-          Settings\r\n-        </Link>\r\n-\r\n-        <Link href=\"/admin/support\" className={linkClass(\"/admin/support\")}>\r\n-          <HelpCircle size={18} />\r\n-          Support\r\n-        </Link>\r\n-\r\n-      </nav>\r\n-    </aside>\r\n-  );\r\n }\n\\ No newline at end of file\n"
                },
                {
                    "date": 1772882239619,
                    "content": "Index: \n===================================================================\n--- \n+++ \n@@ -58,8 +58,13 @@\n         <Link href=\"/admin/categories\" className={linkClass(\"/admin/categories\")}>\r\n           <Layers size={18} />\r\n           Categories\r\n         </Link>\r\n+        \r\n+          <Link href=\"/admin/machines\" className={linkClass(\"/admin/machines\")}>\r\n+          <Tractor size={18} />\r\n+          Machines\r\n+        </Link>\r\n \r\n         <Link href=\"/admin/payments\" className={linkClass(\"/admin/payments\")}>\r\n           <CreditCard size={18} />\r\n           Payments\r\n"
                },
                {
                    "date": 1772882248033,
                    "content": "Index: \n===================================================================\n--- \n+++ \n@@ -49,23 +49,24 @@\n           <Users size={18} />\r\n           Sellers\r\n         </Link>\r\n \r\n-        <Link href=\"/admin/orders\" className={linkClass(\"/admin/orders\")}>\r\n-          <ShoppingCart size={18} />\r\n-          Orders\r\n-        </Link>\r\n \r\n         <Link href=\"/admin/categories\" className={linkClass(\"/admin/categories\")}>\r\n           <Layers size={18} />\r\n           Categories\r\n         </Link>\r\n-        \r\n+\r\n           <Link href=\"/admin/machines\" className={linkClass(\"/admin/machines\")}>\r\n           <Tractor size={18} />\r\n           Machines\r\n         </Link>\r\n \r\n+         <Link href=\"/admin/orders\" className={linkClass(\"/admin/orders\")}>\r\n+          <ShoppingCart size={18} />\r\n+          Orders\r\n+        </Link>\r\n+\r\n         <Link href=\"/admin/payments\" className={linkClass(\"/admin/payments\")}>\r\n           <CreditCard size={18} />\r\n           Payments\r\n         </Link>\r\n"
                },
                {
                    "date": 1772882256338,
                    "content": "Index: \n===================================================================\n--- \n+++ \n@@ -80,13 +80,9 @@\n           <BarChart size={18} />\r\n           Reports\r\n         </Link>\r\n \r\n-        <Link href=\"/admin/settings\" className={linkClass(\"/admin/settings\")}>\r\n-          <Settings size={18} />\r\n-          Settings\r\n-        </Link>\r\n-\r\n+       \r\n         <Link href=\"/admin/support\" className={linkClass(\"/admin/support\")}>\r\n           <HelpCircle size={18} />\r\n           Support\r\n         </Link>\r\n"
                },
                {
                    "date": 1772882267179,
                    "content": "Index: \n===================================================================\n--- \n+++ \n@@ -70,13 +70,8 @@\n           <CreditCard size={18} />\r\n           Payments\r\n         </Link>\r\n \r\n-        <Link href=\"/admin/reviews\" className={linkClass(\"/admin/reviews\")}>\r\n-          <Star size={18} />\r\n-          Reviews\r\n-        </Link>\r\n-\r\n         <Link href=\"/admin/reports\" className={linkClass(\"/admin/reports\")}>\r\n           <BarChart size={18} />\r\n           Reports\r\n         </Link>\r\n"
                },
                {
                    "date": 1772883768996,
                    "content": "Index: \n===================================================================\n--- \n+++ \n@@ -1,88 +1,104 @@\n \"use client\";\r\n \r\n import Link from \"next/link\";\r\n import { usePathname } from \"next/navigation\";\r\n-import { LayoutDashboard, Users, Tractor, ShoppingCart, Layers, CreditCard, Star, BarChart, Settings, HelpCircle, } from \"lucide-react\";\r\n+import {\r\n+  LayoutDashboard,\r\n+  Users,\r\n+  Tractor,\r\n+  ShoppingCart,\r\n+  Layers,\r\n+  CreditCard,\r\n+  Star,\r\n+  BarChart,\r\n+  Settings,\r\n+  HelpCircle\r\n+} from \"lucide-react\";\r\n import Image from \"next/image\";\r\n \r\n export default function AdminSidebar() {\r\n   const pathname = usePathname();\r\n \r\n   const linkClass = (path: string) =>\r\n-    `flex items-center gap-3 px-4 py-3 rounded-xl text-sm font-semibold transition-all duration-200 ${pathname === path\r\n-      ? \"bg-lime-500 text-slate-950 shadow-xl shadow-lime-500/20 scale-[1.02]\"\r\n-      : \"text-slate-400 hover:text-white hover:bg-slate-900\"\r\n+    `flex items-center gap-2.5 px-3 py-2 rounded-lg text-[10px] font-black uppercase tracking-[0.12em] transition-all duration-300 ${pathname === path\r\n+      ? \"bg-white/10 text-lime-400 shadow-sm border border-white/5 backdrop-blur-md\"\r\n+      : \"text-white hover:text-white hover:bg-white/5\"\r\n     }`;\r\n \r\n   return (\r\n-    <aside className=\"w-72 bg-slate-950 text-slate-100 h-screen sticky top-0 p-8 flex flex-col border-r border-slate-900 overflow-y-auto no-scrollbar\">\r\n+    <aside className=\"w-60 bg-slate-950 text-slate-100 h-screen sticky top-0 p-5 flex flex-col border-r border-white/5 overflow-y-auto no-scrollbar shadow-2xl\">\r\n \r\n-      <div className=\"mb-14 px-2\">\r\n-        <div className=\"flex items-center gap-4 group cursor-pointer\">\r\n-          <div className=\"relative w-12 h-12 bg-white p-2 rounded-2xl shadow-xl shadow-lime-500/10 group-hover:scale-110 transition-transform duration-300\">\r\n-            <Image\r\n-              src=\"/images/logo.png\"\r\n-              alt=\"Logo\"\r\n-              fill\r\n-              className=\"object-contain p-1\"\r\n-            />\r\n-          </div>\r\n-          <h2 className=\"text-2xl font-black tracking-tighter text-white\">\r\n-            Agro<span className=\"text-lime-500\">Share</span>\r\n-          </h2>\r\n+      <div className=\"mb-8 px-1 flex items-center gap-3 group cursor-pointer\">\r\n+        <div className=\"relative w-9 h-9 bg-white p-2 rounded-xl shadow-lg shadow-lime-500/5 group-hover:scale-105 transition-transform duration-500 overflow-hidden\">\r\n+          <Image\r\n+            src=\"/images/logo.png\"\r\n+            alt=\"AgroShare Logo\"\r\n+            fill\r\n+            className=\"object-contain p-1.5\"\r\n+          />\r\n         </div>\r\n+        <h2 className=\"text-lg font-black tracking-tighter text-white\">\r\n+          Agro<span className=\"text-lime-500\">Share</span>\r\n+        </h2>\r\n       </div>\r\n \r\n-      <nav className=\"space-y-2\">\r\n-\r\n+      <nav className=\"flex-1 space-y-1\">\r\n         <Link href=\"/admin/dashboard\" className={linkClass(\"/admin/dashboard\")}>\r\n-          <LayoutDashboard size={18} />\r\n-          Dashboard\r\n+          <LayoutDashboard size={14} strokeWidth={2.5} />\r\n+          <span>Dashboard</span>\r\n         </Link>\r\n \r\n         <Link href=\"/admin/users\" className={linkClass(\"/admin/users\")}>\r\n-          <Users size={18} />\r\n-          Users\r\n+          <Users size={14} strokeWidth={2.5} />\r\n+          <span>Users</span>\r\n         </Link>\r\n \r\n         <Link href=\"/admin/sellers\" className={linkClass(\"/admin/sellers\")}>\r\n-          <Users size={18} />\r\n-          Sellers\r\n+          <Users size={14} strokeWidth={2.5} />\r\n+          <span>Sellers</span>\r\n         </Link>\r\n \r\n-\r\n-        <Link href=\"/admin/categories\" className={linkClass(\"/admin/categories\")}>\r\n-          <Layers size={18} />\r\n-          Categories\r\n+        <Link href=\"/admin/machines\" className={linkClass(\"/admin/machines\")}>\r\n+          <Tractor size={14} strokeWidth={2.5} />\r\n+          <span>Machines</span>\r\n         </Link>\r\n \r\n-          <Link href=\"/admin/machines\" className={linkClass(\"/admin/machines\")}>\r\n-          <Tractor size={18} />\r\n-          Machines\r\n+        <Link href=\"/admin/orders\" className={linkClass(\"/admin/orders\")}>\r\n+          <ShoppingCart size={14} strokeWidth={2.5} />\r\n+          <span>Orders</span>\r\n         </Link>\r\n \r\n-         <Link href=\"/admin/orders\" className={linkClass(\"/admin/orders\")}>\r\n-          <ShoppingCart size={18} />\r\n-          Orders\r\n+        <Link href=\"/admin/categories\" className={linkClass(\"/admin/categories\")}>\r\n+          <Layers size={14} strokeWidth={2.5} />\r\n+          <span>Categories</span>\r\n         </Link>\r\n \r\n         <Link href=\"/admin/payments\" className={linkClass(\"/admin/payments\")}>\r\n-          <CreditCard size={18} />\r\n-          Payments\r\n+          <CreditCard size={14} strokeWidth={2.5} />\r\n+          <span>Payments</span>\r\n         </Link>\r\n \r\n+        <Link href=\"/admin/reviews\" className={linkClass(\"/admin/reviews\")}>\r\n+          <Star size={14} strokeWidth={2.5} />\r\n+          <span>Reviews</span>\r\n+        </Link>\r\n+\r\n         <Link href=\"/admin/reports\" className={linkClass(\"/admin/reports\")}>\r\n-          <BarChart size={18} />\r\n-          Reports\r\n+          <BarChart size={14} strokeWidth={2.5} />\r\n+          <span>Reports</span>\r\n         </Link>\r\n+      </nav>\r\n \r\n-       \r\n+      <div className=\"mt-auto pt-5 border-t border-white/5 space-y-1\">\r\n+        <Link href=\"/admin/settings\" className={linkClass(\"/admin/settings\")}>\r\n+          <Settings size={14} strokeWidth={2.5} />\r\n+          <span>Settings</span>\r\n+        </Link>\r\n         <Link href=\"/admin/support\" className={linkClass(\"/admin/support\")}>\r\n-          <HelpCircle size={18} />\r\n-          Support\r\n+          <HelpCircle size={14} strokeWidth={2.5} />\r\n+          <span>Support</span>\r\n         </Link>\r\n-\r\n-      </nav>\r\n+      </div>\r\n     </aside>\r\n   );\r\n }\n\\ No newline at end of file\n"
                },
                {
                    "date": 1772956254577,
                    "content": "Index: \n===================================================================\n--- \n+++ \n@@ -19,27 +19,27 @@\n export default function AdminSidebar() {\r\n   const pathname = usePathname();\r\n \r\n   const linkClass = (path: string) =>\r\n-    `flex items-center gap-2.5 px-3 py-2 rounded-lg text-[10px] font-black uppercase tracking-[0.12em] transition-all duration-300 ${pathname === path\r\n-      ? \"bg-white/10 text-lime-400 shadow-sm border border-white/5 backdrop-blur-md\"\r\n-      : \"text-white hover:text-white hover:bg-white/5\"\r\n+    `flex items-center gap-2.5 px-4 py-2.5 rounded-xl text-[10.5px] font-bold uppercase tracking-[0.08em] transition-all duration-300 ${pathname === path\r\n+      ? \"bg-primary/10 text-primary shadow-sm border border-primary/5\"\r\n+      : \"text-slate-900 hover:text-primary hover:bg-slate-50\"\r\n     }`;\r\n \r\n   return (\r\n-    <aside className=\"w-60 bg-slate-950 text-slate-100 h-screen sticky top-0 p-5 flex flex-col border-r border-white/5 overflow-y-auto no-scrollbar shadow-2xl\">\r\n+    <aside className=\"w-64 bg-white text-slate-900 h-screen sticky top-0 p-6 flex flex-col border-r border-slate-100 overflow-y-auto no-scrollbar shadow-sm\">\r\n \r\n-      <div className=\"mb-8 px-1 flex items-center gap-3 group cursor-pointer\">\r\n-        <div className=\"relative w-9 h-9 bg-white p-2 rounded-xl shadow-lg shadow-lime-500/5 group-hover:scale-105 transition-transform duration-500 overflow-hidden\">\r\n+      <div className=\"mb-10 px-1 flex items-center gap-3 group cursor-pointer\">\r\n+        <div className=\"relative w-10 h-10 bg-primary/10 p-2 rounded-xl shadow-sm group-hover:scale-105 transition-transform duration-500 overflow-hidden\">\r\n           <Image\r\n             src=\"/images/logo.png\"\r\n             alt=\"AgroShare Logo\"\r\n             fill\r\n-            className=\"object-contain p-1.5\"\r\n+            className=\"object-contain p-2\"\r\n           />\r\n         </div>\r\n-        <h2 className=\"text-lg font-black tracking-tighter text-white\">\r\n-          Agro<span className=\"text-lime-500\">Share</span>\r\n+        <h2 className=\"text-xl font-black tracking-tighter text-slate-900\">\r\n+          Agro<span className=\"text-primary\">Share</span>\r\n         </h2>\r\n       </div>\r\n \r\n       <nav className=\"flex-1 space-y-1\">\r\n@@ -88,9 +88,9 @@\n           <span>Reports</span>\r\n         </Link>\r\n       </nav>\r\n \r\n-      <div className=\"mt-auto pt-5 border-t border-white/5 space-y-1\">\r\n+      <div className=\"mt-auto pt-6 border-t border-slate-100 space-y-1\">\r\n         <Link href=\"/admin/settings\" className={linkClass(\"/admin/settings\")}>\r\n           <Settings size={14} strokeWidth={2.5} />\r\n           <span>Settings</span>\r\n         </Link>\r\n"
                },
                {
                    "date": 1772956296727,
                    "content": "Index: \n===================================================================\n--- \n+++ \n@@ -57,18 +57,8 @@\n           <Users size={14} strokeWidth={2.5} />\r\n           <span>Sellers</span>\r\n         </Link>\r\n \r\n-        <Link href=\"/admin/machines\" className={linkClass(\"/admin/machines\")}>\r\n-          <Tractor size={14} strokeWidth={2.5} />\r\n-          <span>Machines</span>\r\n-        </Link>\r\n-\r\n-        <Link href=\"/admin/orders\" className={linkClass(\"/admin/orders\")}>\r\n-          <ShoppingCart size={14} strokeWidth={2.5} />\r\n-          <span>Orders</span>\r\n-        </Link>\r\n-\r\n         <Link href=\"/admin/categories\" className={linkClass(\"/admin/categories\")}>\r\n           <Layers size={14} strokeWidth={2.5} />\r\n           <span>Categories</span>\r\n         </Link>\r\n"
                },
                {
                    "date": 1772956312766,
                    "content": "Index: \n===================================================================\n--- \n+++ \n@@ -0,0 +1,95 @@\n+\"use client\";\r\n+\r\n+import Link from \"next/link\";\r\n+import { usePathname } from \"next/navigation\";\r\n+import {\r\n+  LayoutDashboard,\r\n+  Users,\r\n+  Tractor,\r\n+  ShoppingCart,\r\n+  Layers,\r\n+  CreditCard,\r\n+  Star,\r\n+  BarChart,\r\n+  Settings,\r\n+  HelpCircle\r\n+} from \"lucide-react\";\r\n+import Image from \"next/image\";\r\n+\r\n+export default function AdminSidebar() {\r\n+  const pathname = usePathname();\r\n+\r\n+  const linkClass = (path: string) =>\r\n+    `flex items-center gap-2.5 px-4 py-2.5 rounded-xl text-[10.5px] font-bold uppercase tracking-[0.08em] transition-all duration-300 ${pathname === path\r\n+      ? \"bg-primary/10 text-primary shadow-sm border border-primary/5\"\r\n+      : \"text-slate-900 hover:text-primary hover:bg-slate-50\"\r\n+    }`;\r\n+\r\n+  return (\r\n+    <aside className=\"w-64 bg-white text-slate-900 h-screen sticky top-0 p-6 flex flex-col border-r border-slate-100 overflow-y-auto no-scrollbar shadow-sm\">\r\n+\r\n+      <div className=\"mb-10 px-1 flex items-center gap-3 group cursor-pointer\">\r\n+        <div className=\"relative w-10 h-10 bg-primary/10 p-2 rounded-xl shadow-sm group-hover:scale-105 transition-transform duration-500 overflow-hidden\">\r\n+          <Image\r\n+            src=\"/images/logo.png\"\r\n+            alt=\"AgroShare Logo\"\r\n+            fill\r\n+            className=\"object-contain p-2\"\r\n+          />\r\n+        </div>\r\n+        <h2 className=\"text-xl font-black tracking-tighter text-slate-900\">\r\n+          Agro<span className=\"text-primary\">Share</span>\r\n+        </h2>\r\n+      </div>\r\n+\r\n+      <nav className=\"flex-1 space-y-1\">\r\n+        <Link href=\"/admin/dashboard\" className={linkClass(\"/admin/dashboard\")}>\r\n+          <LayoutDashboard size={14} strokeWidth={2.5} />\r\n+          <span>Dashboard</span>\r\n+        </Link>\r\n+\r\n+        <Link href=\"/admin/users\" className={linkClass(\"/admin/users\")}>\r\n+          <Users size={14} strokeWidth={2.5} />\r\n+          <span>Users</span>\r\n+        </Link>\r\n+\r\n+        <Link href=\"/admin/sellers\" className={linkClass(\"/admin/sellers\")}>\r\n+          <Users size={14} strokeWidth={2.5} />\r\n+          <span>Sellers</span>\r\n+        </Link>\r\n+\r\n+\r\n+        <Link href=\"/admin/categories\" className={linkClass(\"/admin/categories\")}>\r\n+          <Layers size={14} strokeWidth={2.5} />\r\n+          <span>Categories</span>\r\n+        </Link>\r\n+\r\n+        <Link href=\"/admin/payments\" className={linkClass(\"/admin/payments\")}>\r\n+          <CreditCard size={14} strokeWidth={2.5} />\r\n+          <span>Payments</span>\r\n+        </Link>\r\n+\r\n+        <Link href=\"/admin/reviews\" className={linkClass(\"/admin/reviews\")}>\r\n+          <Star size={14} strokeWidth={2.5} />\r\n+          <span>Reviews</span>\r\n+        </Link>\r\n+\r\n+        <Link href=\"/admin/reports\" className={linkClass(\"/admin/reports\")}>\r\n+          <BarChart size={14} strokeWidth={2.5} />\r\n+          <span>Reports</span>\r\n+        </Link>\r\n+      </nav>\r\n+\r\n+      <div className=\"mt-auto pt-6 border-t border-slate-100 space-y-1\">\r\n+        <Link href=\"/admin/settings\" className={linkClass(\"/admin/settings\")}>\r\n+          <Settings size={14} strokeWidth={2.5} />\r\n+          <span>Settings</span>\r\n+        </Link>\r\n+        <Link href=\"/admin/support\" className={linkClass(\"/admin/support\")}>\r\n+          <HelpCircle size={14} strokeWidth={2.5} />\r\n+          <span>Support</span>\r\n+        </Link>\r\n+      </div>\r\n+    </aside>\r\n+  );\r\n+}\n\\ No newline at end of file\n"
                },
                {
                    "date": 1772956335475,
                    "content": "Index: \n===================================================================\n--- \n+++ \n@@ -57,108 +57,26 @@\n           <Users size={14} strokeWidth={2.5} />\r\n           <span>Sellers</span>\r\n         </Link>\r\n \r\n+      \r\n \r\n         <Link href=\"/admin/categories\" className={linkClass(\"/admin/categories\")}>\r\n           <Layers size={14} strokeWidth={2.5} />\r\n           <span>Categories</span>\r\n         </Link>\r\n \r\n-        <Link href=\"/admin/payments\" className={linkClass(\"/admin/payments\")}>\r\n-          <CreditCard size={14} strokeWidth={2.5} />\r\n-          <span>Payments</span>\r\n-        </Link>\r\n \r\n-        <Link href=\"/admin/reviews\" className={linkClass(\"/admin/reviews\")}>\r\n-          <Star size={14} strokeWidth={2.5} />\r\n-          <span>Reviews</span>\r\n+          <Link href=\"/admin/machines\" className={linkClass(\"/admin/machines\")}>\r\n+          <Tractor size={14} strokeWidth={2.5} />\r\n+          <span>Machines</span>\r\n         </Link>\r\n \r\n-        <Link href=\"/admin/reports\" className={linkClass(\"/admin/reports\")}>\r\n-          <BarChart size={14} strokeWidth={2.5} />\r\n-          <span>Reports</span>\r\n+        <Link href=\"/admin/orders\" className={linkClass(\"/admin/orders\")}>\r\n+          <ShoppingCart size={14} strokeWidth={2.5} />\r\n+          <span>Orders</span>\r\n         </Link>\r\n-      </nav>\r\n \r\n-      <div className=\"mt-auto pt-6 border-t border-slate-100 space-y-1\">\r\n-        <Link href=\"/admin/settings\" className={linkClass(\"/admin/settings\")}>\r\n-          <Settings size={14} strokeWidth={2.5} />\r\n-          <span>Settings</span>\r\n-        </Link>\r\n-        <Link href=\"/admin/support\" className={linkClass(\"/admin/support\")}>\r\n-          <HelpCircle size={14} strokeWidth={2.5} />\r\n-          <span>Support</span>\r\n-        </Link>\r\n-      </div>\r\n-    </aside>\r\n-  );\r\n-}\n-\"use client\";\r\n-\r\n-import Link from \"next/link\";\r\n-import { usePathname } from \"next/navigation\";\r\n-import {\r\n-  LayoutDashboard,\r\n-  Users,\r\n-  Tractor,\r\n-  ShoppingCart,\r\n-  Layers,\r\n-  CreditCard,\r\n-  Star,\r\n-  BarChart,\r\n-  Settings,\r\n-  HelpCircle\r\n-} from \"lucide-react\";\r\n-import Image from \"next/image\";\r\n-\r\n-export default function AdminSidebar() {\r\n-  const pathname = usePathname();\r\n-\r\n-  const linkClass = (path: string) =>\r\n-    `flex items-center gap-2.5 px-4 py-2.5 rounded-xl text-[10.5px] font-bold uppercase tracking-[0.08em] transition-all duration-300 ${pathname === path\r\n-      ? \"bg-primary/10 text-primary shadow-sm border border-primary/5\"\r\n-      : \"text-slate-900 hover:text-primary hover:bg-slate-50\"\r\n-    }`;\r\n-\r\n-  return (\r\n-    <aside className=\"w-64 bg-white text-slate-900 h-screen sticky top-0 p-6 flex flex-col border-r border-slate-100 overflow-y-auto no-scrollbar shadow-sm\">\r\n-\r\n-      <div className=\"mb-10 px-1 flex items-center gap-3 group cursor-pointer\">\r\n-        <div className=\"relative w-10 h-10 bg-primary/10 p-2 rounded-xl shadow-sm group-hover:scale-105 transition-transform duration-500 overflow-hidden\">\r\n-          <Image\r\n-            src=\"/images/logo.png\"\r\n-            alt=\"AgroShare Logo\"\r\n-            fill\r\n-            className=\"object-contain p-2\"\r\n-          />\r\n-        </div>\r\n-        <h2 className=\"text-xl font-black tracking-tighter text-slate-900\">\r\n-          Agro<span className=\"text-primary\">Share</span>\r\n-        </h2>\r\n-      </div>\r\n-\r\n-      <nav className=\"flex-1 space-y-1\">\r\n-        <Link href=\"/admin/dashboard\" className={linkClass(\"/admin/dashboard\")}>\r\n-          <LayoutDashboard size={14} strokeWidth={2.5} />\r\n-          <span>Dashboard</span>\r\n-        </Link>\r\n-\r\n-        <Link href=\"/admin/users\" className={linkClass(\"/admin/users\")}>\r\n-          <Users size={14} strokeWidth={2.5} />\r\n-          <span>Users</span>\r\n-        </Link>\r\n-\r\n-        <Link href=\"/admin/sellers\" className={linkClass(\"/admin/sellers\")}>\r\n-          <Users size={14} strokeWidth={2.5} />\r\n-          <span>Sellers</span>\r\n-        </Link>\r\n-\r\n-        <Link href=\"/admin/categories\" className={linkClass(\"/admin/categories\")}>\r\n-          <Layers size={14} strokeWidth={2.5} />\r\n-          <span>Categories</span>\r\n-        </Link>\r\n-\r\n         <Link href=\"/admin/payments\" className={linkClass(\"/admin/payments\")}>\r\n           <CreditCard size={14} strokeWidth={2.5} />\r\n           <span>Payments</span>\r\n         </Link>\r\n"
                }
            ],
            "date": 1772794830236,
            "name": "Commit-0",
            "content": "AdminNav"
        }
    ]
}